fdavg/__init__.py
fdavg/main.py
fdavg/metrics/__init__.py
fdavg/metrics/epoch_metrics.py
fdavg/models/__init__.py
fdavg/models/advanced_cnn.py
fdavg/models/dense_net.py
fdavg/models/lenet5.py
fdavg/models/miscellaneous.py
fdavg/strategies/__init__.py
fdavg/strategies/gm.py
fdavg/strategies/linear.py
fdavg/strategies/naive.py
fdavg/strategies/simulation.py
fdavg/strategies/sketch.py
fdavg/strategies/synchronous.py
fdavg-0.45.dist-info/METADATA
fdavg-0.45.dist-info/WHEEL
fdavg-0.45.dist-info/top_level.txt
fdavg-0.45.dist-info/RECORD
