Metadata-Version: 2.1
Name: fdavg
Version: 0.45
Requires-Dist: tensorflow
Requires-Dist: numpy
